RoseDriver/RoseBuilder.py
RoseDriver/__init__.py
RoseDriver/interface.py
python_rosedriver-1.0.1.dist-info/LICENSE
python_rosedriver-1.0.1.dist-info/METADATA
python_rosedriver-1.0.1.dist-info/WHEEL
python_rosedriver-1.0.1.dist-info/top_level.txt
python_rosedriver-1.0.1.dist-info/RECORD
