Metadata-Version: 2.1
Name: python-rosedriver
Version: 1.0.1
Summary: A simple, unsophisticated python driver for RoseDB
Home-page: https://github.com/LittleCrowRevi/Python-RoseDB-Driver
Author: Revi Snow
Author-email: snowrevy@gmail.com
License: UNKNOWN
Project-URL: Bug Tracker, https://github.com/LittleCrowRevi/Python-RoseDB-Driver/issues
Platform: UNKNOWN
Classifier: Programming Language :: Python :: 3
Classifier: License :: OSI Approved :: Apache Software License
Classifier: Operating System :: OS Independent
Requires-Python: >=3.9
License-File: LICENSE
